{"name":"Comprar productos online desde la pagina web","id":"compra-de-productos-online;comprar-productos-online-desde-la-pagina-web","testSteps":[{"number":1,"description":"Given abro la aplicacion","duration":16398,"startTime":"2021-03-22T20:40:14.306-05:00[America/Bogota]","result":"SUCCESS","precondition":false,"level":0},{"number":2,"description":"When escojo un producto o productos que quiero comprar","duration":24286,"startTime":"2021-03-22T20:40:30.714-05:00[America/Bogota]","result":"SUCCESS","precondition":false,"level":0,"children":[{"number":3,"description":"Esteban Laverde Selecciona Categoria de los productos que desea comprar","duration":23926,"startTime":"2021-03-22T20:40:31.071-05:00[America/Bogota]","screenshots":[{"screenshot":"dc675897d6507d00b004356a4edeed945ddf0146427e50341959fefb83ac7002.png","timeStamp":1616463634974},{"screenshot":"dc675897d6507d00b004356a4edeed945ddf0146427e50341959fefb83ac7002.png","timeStamp":1616463634977}],"result":"SUCCESS","precondition":false,"level":1,"children":[{"number":4,"description":"Esteban Laverde clicks on Aceptar Cookies","duration":523,"startTime":"2021-03-22T20:40:31.526-05:00[America/Bogota]","result":"SUCCESS","precondition":false,"level":2},{"number":5,"description":"Esteban Laverde clicks on Televisores","duration":20012,"startTime":"2021-03-22T20:40:34.983-05:00[America/Bogota]","result":"SUCCESS","precondition":false,"level":2}]}]},{"number":6,"description":"And los agrego al carrito para finalizar la compra","duration":38260,"startTime":"2021-03-22T20:40:55.001-05:00[America/Bogota]","result":"SUCCESS","precondition":false,"level":0,"children":[{"number":7,"description":"Esteban Laverde Agrega producto al carrito","duration":6468,"startTime":"2021-03-22T20:40:55.031-05:00[America/Bogota]","screenshots":[{"screenshot":"7813d912c55de35883e6f41518bd98b0083da84e04dc44d44801ea954a2b8e28.png","timeStamp":1616463656380},{"screenshot":"0fd4f25b952277f6063a1dbdfe5d179d4a045fe7569a30384b5930c8f79c06df.png","timeStamp":1616463661498}],"result":"SUCCESS","precondition":false,"level":1,"children":[{"number":8,"description":"Esteban Laverde Scrolling on Page","duration":23,"startTime":"2021-03-22T20:40:55.076-05:00[America/Bogota]","result":"SUCCESS","precondition":false,"level":2},{"number":9,"description":"Esteban Laverde clicks on COMPUTADOR ASUS","duration":467,"startTime":"2021-03-22T20:40:55.103-05:00[America/Bogota]","result":"SUCCESS","precondition":false,"level":2},{"number":10,"description":"Esteban Laverde Scrolling on Page","duration":38,"startTime":"2021-03-22T20:40:55.582-05:00[America/Bogota]","result":"SUCCESS","precondition":false,"level":2},{"number":11,"description":"Esteban Laverde clicks on Boton Agregar al Carrito","duration":2617,"startTime":"2021-03-22T20:40:56.387-05:00[America/Bogota]","result":"SUCCESS","precondition":false,"level":2},{"number":12,"description":"Esteban laverde esperar","duration":2006,"startTime":"2021-03-22T20:40:59.068-05:00[America/Bogota]","result":"SUCCESS","precondition":false,"level":2}]},{"number":13,"description":"Esteban Laverde Finaliza la compra de los productos","duration":31730,"startTime":"2021-03-22T20:41:01.529-05:00[America/Bogota]","screenshots":[{"screenshot":"654917e48ec627f9483e638dd327285271cfd79d73445cf8d8c83cd05c2dcc1a.png","timeStamp":1616463662091},{"screenshot":"b050c48be28b6ecb51eacec9fb4034b377f09cc3793189b414bb0f7d161e5df6.png","timeStamp":1616463662700},{"screenshot":"5270013d9e65d817d0031a14d9b442a42111485dff16d31d047098dfd8138a76.png","timeStamp":1616463663227},{"screenshot":"baa6be05da5fac451d091351bffbad4d91cb70461dab6efa99468786e3a52264.png","timeStamp":1616463672906},{"screenshot":"b37dbe2b4482aa16d6651e1b53fe14abdb497010e92313e0fee355eef4db1264.png","timeStamp":1616463673589},{"screenshot":"737c03c8db9cd0de49cf3fe1fb598b128b9a093dc09abe0ea6efff821b7577b2.png","timeStamp":1616463674468},{"screenshot":"db9bcd47c1d5d60544df4dd3bd6029b4729719c3a91ff7e6a9088ef9de11e541.png","timeStamp":1616463675318},{"screenshot":"a503b5dffa95509d538366ae7dfd0af890c6342a0067808f83a32ba767abd097.png","timeStamp":1616463680595},{"screenshot":"5421d50457a92eb5be0b5e87d64c3d685ef8f6fb1baff2441b72b24f349f61fe.png","timeStamp":1616463684330},{"screenshot":"d621e8d4aa752ebeb1e4acbe12899c5d6b40a33f1bb3e453f8a5eb423884592c.png","timeStamp":1616463693259}],"result":"SUCCESS","precondition":false,"level":1,"children":[{"number":14,"description":"Esteban Laverde waits the Acepto terminos y condiciones until is Visible","duration":83,"startTime":"2021-03-22T20:41:01.569-05:00[America/Bogota]","result":"SUCCESS","precondition":false,"level":2},{"number":15,"description":"Esteban Laverde clicks on Acepto terminos y condiciones","duration":179,"startTime":"2021-03-22T20:41:02.095-05:00[America/Bogota]","result":"SUCCESS","precondition":false,"level":2},{"number":16,"description":"Esteban Laverde clicks on Boton finalizar compra","duration":105,"startTime":"2021-03-22T20:41:02.703-05:00[America/Bogota]","result":"SUCCESS","precondition":false,"level":2},{"number":17,"description":"Esteban Laverde waits the Campo Email until is Visible","duration":7704,"startTime":"2021-03-22T20:41:03.229-05:00[America/Bogota]","result":"SUCCESS","precondition":false,"level":2},{"number":18,"description":"Esteban Laverde enters \u0027micorreo@gmail.com\u0027 into Campo Email","duration":1383,"startTime":"2021-03-22T20:41:11.107-05:00[America/Bogota]","result":"SUCCESS","precondition":false,"level":2},{"number":19,"description":"Esteban Laverde clicks on BOTON CONTINUAR","duration":186,"startTime":"2021-03-22T20:41:12.910-05:00[America/Bogota]","result":"SUCCESS","precondition":false,"level":2},{"number":20,"description":"Esteban Laverde clicks on BOTON CONTINUAR CON LA COMPRA","duration":261,"startTime":"2021-03-22T20:41:13.676-05:00[America/Bogota]","result":"SUCCESS","precondition":false,"level":2},{"number":21,"description":"Esteban Laverde Scrolling on Page","duration":140,"startTime":"2021-03-22T20:41:14.475-05:00[America/Bogota]","result":"SUCCESS","precondition":false,"level":2},{"number":22,"description":"Esteban Laverde clicks on Dia de la entrega","duration":303,"startTime":"2021-03-22T20:41:14.622-05:00[America/Bogota]","result":"SUCCESS","precondition":false,"level":2},{"number":23,"description":"Esteban Laverde clicks on Boton ir a metodo de pago","duration":4599,"startTime":"2021-03-22T20:41:15.321-05:00[America/Bogota]","result":"SUCCESS","precondition":false,"level":2},{"number":24,"description":"Esteban Laverde waits the Selecciona pago en efectivo until is Visible","duration":56,"startTime":"2021-03-22T20:41:19.923-05:00[America/Bogota]","result":"SUCCESS","precondition":false,"level":2},{"number":25,"description":"Esteban Laverde clicks on Selecciona pago en efectivo","duration":138,"startTime":"2021-03-22T20:41:19.987-05:00[America/Bogota]","result":"SUCCESS","precondition":false,"level":2},{"number":26,"description":"Esteban Laverde waits the Boton comprar ahora until is Enabled","duration":77,"startTime":"2021-03-22T20:41:20.598-05:00[America/Bogota]","result":"SUCCESS","precondition":false,"level":2},{"number":27,"description":"Esteban laverde esperar","duration":3003,"startTime":"2021-03-22T20:41:20.678-05:00[America/Bogota]","result":"SUCCESS","precondition":false,"level":2},{"number":28,"description":"Esteban Laverde clicks on Boton comprar ahora","duration":136,"startTime":"2021-03-22T20:41:23.684-05:00[America/Bogota]","result":"SUCCESS","precondition":false,"level":2},{"number":29,"description":"Esteban laverde esperar","duration":3004,"startTime":"2021-03-22T20:41:24.334-05:00[America/Bogota]","result":"SUCCESS","precondition":false,"level":2},{"number":30,"description":"Esteban laverde esperar","duration":2002,"startTime":"2021-03-22T20:41:27.342-05:00[America/Bogota]","result":"SUCCESS","precondition":false,"level":2}]}]},{"number":31,"description":"Then el sistema me debe mostrar mensaje Su pedido ha sido confirmado con éxito!","duration":1837,"startTime":"2021-03-22T20:41:33.262-05:00[America/Bogota]","result":"SUCCESS","precondition":false,"level":0,"children":[{"number":32,"description":"Then el mensaje should be \u0027Su pedido ha sido confirmado con \u0026eacute;xito!\u0027","duration":127,"startTime":"2021-03-22T20:41:34.970-05:00[America/Bogota]","result":"SUCCESS","precondition":false,"level":1}]}],"userStory":{"id":"compra-de-productos-online","storyName":"compra de productos online","path":"src/test/resources/features/compra.feature","narrative":"  Yo como usuario quiero ingresar a la pagina web para poder comprar productoS","type":"feature"},"featureTag":{"name":"Features/compra de productos online","type":"feature","displayName":"Features/compra de productos online"},"title":"Comprar productos online desde la pagina web","tags":[{"name":"compra de productos online","type":"feature","displayName":"compra de productos online"}],"startTime":"2021-03-22T20:40:13.944-05:00[America/Bogota]","duration":81155,"projectKey":"","sessionId":"b87711b36c2d13a0cc744a7eb55669af","driver":"chrome","manual":false,"testSource":"Cucumber","actors":[{"name":"Esteban Laverde","can":["browse the web"]}],"result":"SUCCESS"}